AUTHORS.md
LICENSE
README.md
pyproject.toml
treeffuser/__init__.py
treeffuser/_base_tabular_diffusion.py
treeffuser/_scaler.py
treeffuser/_score_models.py
treeffuser/_warnings.py
treeffuser/samples.py
treeffuser/sde/__init__.py
treeffuser/sde/base_sde.py
treeffuser/sde/base_solver.py
treeffuser/sde/diffusion_sdes.py
treeffuser/sde/initialize.py
treeffuser/sde/parameter_schedule.py
treeffuser/sde/solvers.py
treeffuser/treeffuser.py
treeffuser-0.2.0.dist-info/AUTHORS.md
treeffuser-0.2.0.dist-info/LICENSE
treeffuser-0.2.0.dist-info/METADATA
treeffuser-0.2.0.dist-info/WHEEL
treeffuser-0.2.0.dist-info/RECORD
