Metadata-Version: 2.1
Name: treeffuser
Version: 0.2.0
Summary: Probabilistic predictions for tabular data, using diffusion models and decision trees.
Home-page: https://blei-lab.github.io/treeffuser/
License: MIT
Author: Nicolas Beltran-Velez
Author-email: nb2838@columbia.edu
Requires-Python: >=3.9,<4.0
Classifier: License :: OSI Approved :: MIT License
Classifier: Programming Language :: Python :: 3
Classifier: Programming Language :: Python :: 3.9
Classifier: Programming Language :: Python :: 3.10
Classifier: Programming Language :: Python :: 3.11
Classifier: Programming Language :: Python :: 3.12
Requires-Dist: einops (>=0.8.0,<0.9.0)
Requires-Dist: jaxtyping (>=0.2.19,<0.3.0)
Requires-Dist: lightgbm (==4.3.0)
Requires-Dist: ml-collections (>=0.1.1,<0.2.0)
Requires-Dist: numpy (>=1.24,<2.0)
Requires-Dist: pandas (>=2.0.0,<3.0.0)
Requires-Dist: scikit-learn (==1.5.0)
Requires-Dist: scipy (>=1.13,<2.0)
Requires-Dist: tqdm (>=4.66.4,<5.0.0)
Project-URL: Repository, https://github.com/blei-lab/treeffuser
